README.md
setup.py
crawlbase/__init__.py
crawlbase/base_api.py
crawlbase/crawling_api.py
crawlbase/leads_api.py
crawlbase/scraper_api.py
crawlbase/screenshots_api.py
crawlbase/storage_api.py
crawlbase.egg-info/PKG-INFO
crawlbase.egg-info/SOURCES.txt
crawlbase.egg-info/dependency_links.txt
crawlbase.egg-info/top_level.txt