Metadata-Version: 2.1
Name: crawlbase
Version: 1.0.0
Summary: A Python class that acts as wrapper for Crawlbase scraping and crawling API
Home-page: https://github.com/crawlbase-source/crawlbase-python
Author: Crawlbase
Author-email: info@crawlbase.com
License: Apache-2.0
Keywords: scraping scraper crawler crawling crawlbase api
Platform: UNKNOWN
Classifier: Programming Language :: Python :: 2
Classifier: Programming Language :: Python :: 2.7
Classifier: Programming Language :: Python :: 3
Classifier: Programming Language :: Python :: 3.5
Classifier: Programming Language :: Python :: 3.9
Classifier: Development Status :: 5 - Production/Stable
Classifier: Intended Audience :: Developers
Classifier: License :: OSI Approved :: Apache Software License
Classifier: Operating System :: OS Independent
Classifier: Topic :: Utilities
